docset/__init__.py
docset/codec.py
docset/docset.py
docset/docset_legacy.py
docset/entries.py
docset-0.5.5.dist-info/LICENSE
docset-0.5.5.dist-info/METADATA
docset-0.5.5.dist-info/WHEEL
docset-0.5.5.dist-info/entry_points.txt
docset-0.5.5.dist-info/top_level.txt
docset-0.5.5.dist-info/zip-safe
docset-0.5.5.dist-info/RECORD
