Metadata-Version: 2.1
Name: docset
Version: 0.5.5
Summary: A dataset format/utilities used to store document objects based on BSON.
Home-page: https://github.com/XoriieInpottn/docset
Author: xi
Author-email: gylv@mail.ustc.edu.cn
License: BSD-3-Clause License
Keywords: dataset,file format
Platform: any
Classifier: Programming Language :: Python :: 3.6
Classifier: Programming Language :: Python :: 3.7
Classifier: Programming Language :: Python :: 3.8
License-File: LICENSE
Requires-Dist: numpy
Requires-Dist: pymongo
Requires-Dist: tqdm
